request_replay/__init__.py
request_replay/json_request.py
request_replay/url_request.py
request_replay-0.1.3.dist-info/METADATA
request_replay-0.1.3.dist-info/WHEEL
request_replay-0.1.3.dist-info/top_level.txt
request_replay-0.1.3.dist-info/RECORD
