Metadata-Version: 2.1
Name: request-replay
Version: 0.1.3
Summary: UNKNOWN
Home-page: UNKNOWN
Author: htamlive
License: UNKNOWN
Platform: UNKNOWN
Requires-Dist: httpx
Requires-Dist: tqdm
Requires-Dist: httpx[http2]
